{
"meta":{"test_sets":[],"test_metrics":[],"learn_metrics":[{"best_value":"Min","name":"MultiClass"}],"launch_mode":"Train","parameters":"","iteration_count":122,"learn_sets":["learn"],"name":"experiment"},
"iterations":[
{"learn":[1.081374098],"iteration":0,"passed_time":0.2140322472,"remaining_time":25.89790191},
{"learn":[1.067817405],"iteration":1,"passed_time":0.2524369346,"remaining_time":15.14621607},
{"learn":[1.05536011],"iteration":2,"passed_time":0.2916276737,"remaining_time":11.56789772},
{"learn":[1.044255234],"iteration":3,"passed_time":0.3352480247,"remaining_time":9.88981673},
{"learn":[1.03442121],"iteration":4,"passed_time":0.3781332004,"remaining_time":8.84831689},
{"learn":[1.025793243],"iteration":5,"passed_time":0.4218658905,"remaining_time":8.156073883},
{"learn":[1.018715892],"iteration":6,"passed_time":0.4604549664,"remaining_time":7.564617306},
{"learn":[1.01190645],"iteration":7,"passed_time":0.5022254417,"remaining_time":7.156712545},
{"learn":[1.00575953],"iteration":8,"passed_time":0.5462041641,"remaining_time":6.857896727},
{"learn":[1.000144192],"iteration":9,"passed_time":0.5956009906,"remaining_time":6.670731094},
{"learn":[0.9953090945],"iteration":10,"passed_time":0.6421245129,"remaining_time":6.479620085},
{"learn":[0.9913000516],"iteration":11,"passed_time":0.687570578,"remaining_time":6.302730298},
{"learn":[0.9870740084],"iteration":12,"passed_time":0.7321722169,"remaining_time":6.138982434},
{"learn":[0.9831376518],"iteration":13,"passed_time":0.7806104442,"remaining_time":6.021851998},
{"learn":[0.9793649034],"iteration":14,"passed_time":0.8292248692,"remaining_time":5.9151374},
{"learn":[0.97524458],"iteration":15,"passed_time":0.8756366635,"remaining_time":5.801092895},
{"learn":[0.9716594172],"iteration":16,"passed_time":0.9233731774,"remaining_time":5.703187272},
{"learn":[0.9694031988],"iteration":17,"passed_time":0.9714659674,"remaining_time":5.612914478},
{"learn":[0.9670171223],"iteration":18,"passed_time":1.015250777,"remaining_time":5.503727896},
{"learn":[0.9645279273],"iteration":19,"passed_time":1.054806984,"remaining_time":5.379515617},
{"learn":[0.9611290165],"iteration":20,"passed_time":1.096260222,"remaining_time":5.27248964},
{"learn":[0.9598106469],"iteration":21,"passed_time":1.13828895,"remaining_time":5.174040683},
{"learn":[0.9573898371],"iteration":22,"passed_time":1.191184679,"remaining_time":5.127273182},
{"learn":[0.9554775228],"iteration":23,"passed_time":1.237544394,"remaining_time":5.053306274},
{"learn":[0.9529909805],"iteration":24,"passed_time":1.278894015,"remaining_time":4.962108778},
{"learn":[0.9516021468],"iteration":25,"passed_time":1.316883401,"remaining_time":4.862338713},
{"learn":[0.9498132907],"iteration":26,"passed_time":1.354607737,"remaining_time":4.766212406},
{"learn":[0.9469665279],"iteration":27,"passed_time":1.396149977,"remaining_time":4.687074922},
{"learn":[0.9452887348],"iteration":28,"passed_time":1.439066429,"remaining_time":4.61493717},
{"learn":[0.9432025317],"iteration":29,"passed_time":1.482722629,"remaining_time":4.547016062},
{"learn":[0.9415974188],"iteration":30,"passed_time":1.526412584,"remaining_time":4.480759519},
{"learn":[0.9403003753],"iteration":31,"passed_time":1.56703578,"remaining_time":4.407288133},
{"learn":[0.9384969787],"iteration":32,"passed_time":1.60650459,"remaining_time":4.332694196},
{"learn":[0.9374594922],"iteration":33,"passed_time":1.645026418,"remaining_time":4.257715435},
{"learn":[0.9361008946],"iteration":34,"passed_time":1.685873882,"remaining_time":4.190600792},
{"learn":[0.9347218163],"iteration":35,"passed_time":1.730480112,"remaining_time":4.133924711},
{"learn":[0.9327391505],"iteration":36,"passed_time":1.770835955,"remaining_time":4.068136652},
{"learn":[0.9307319711],"iteration":37,"passed_time":1.812764965,"remaining_time":4.007164659},
{"learn":[0.9301040875],"iteration":38,"passed_time":1.854071791,"remaining_time":3.945845093},
{"learn":[0.9287279727],"iteration":39,"passed_time":1.89335574,"remaining_time":3.881379268},
{"learn":[0.9277548996],"iteration":40,"passed_time":1.934218161,"remaining_time":3.82126027},
{"learn":[0.925912782],"iteration":41,"passed_time":1.986017256,"remaining_time":3.782890012},
{"learn":[0.9250091572],"iteration":42,"passed_time":2.044054449,"remaining_time":3.755355848},
{"learn":[0.9231477048],"iteration":43,"passed_time":2.094128826,"remaining_time":3.712319282},
{"learn":[0.9215831869],"iteration":44,"passed_time":2.147795469,"remaining_time":3.675116692},
{"learn":[0.9199524335],"iteration":45,"passed_time":2.20343794,"remaining_time":3.640462684},
{"learn":[0.9190976123],"iteration":46,"passed_time":2.250557975,"remaining_time":3.591315917},
{"learn":[0.9182255864],"iteration":47,"passed_time":2.290713158,"remaining_time":3.531516118},
{"learn":[0.9169015773],"iteration":48,"passed_time":2.330017379,"remaining_time":3.471250381},
{"learn":[0.9162251058],"iteration":49,"passed_time":2.369934612,"remaining_time":3.412705841},
{"learn":[0.9152347153],"iteration":50,"passed_time":2.413880352,"remaining_time":3.360500097},
{"learn":[0.9145412072],"iteration":51,"passed_time":2.461373045,"remaining_time":3.313386791},
{"learn":[0.9132295514],"iteration":52,"passed_time":2.512697426,"remaining_time":3.271247593},
{"learn":[0.9123162937],"iteration":53,"passed_time":2.558161528,"remaining_time":3.221388591},
{"learn":[0.9109373888],"iteration":54,"passed_time":2.602956846,"remaining_time":3.170874703},
{"learn":[0.9100539737],"iteration":55,"passed_time":2.643183959,"remaining_time":3.115181095},
{"learn":[0.9092969714],"iteration":56,"passed_time":2.685827739,"remaining_time":3.062786018},
{"learn":[0.907580177],"iteration":57,"passed_time":2.731735241,"remaining_time":3.014328541},
{"learn":[0.9065838906],"iteration":58,"passed_time":2.775691552,"remaining_time":2.96387403},
{"learn":[0.9053540242],"iteration":59,"passed_time":2.817360246,"remaining_time":2.911272254},
{"learn":[0.9042187742],"iteration":60,"passed_time":2.859226109,"remaining_time":2.859226109},
{"learn":[0.9028189804],"iteration":61,"passed_time":2.900651489,"remaining_time":2.807082086},
{"learn":[0.9019830454],"iteration":62,"passed_time":2.943463814,"remaining_time":2.756577223},
{"learn":[0.9008035001],"iteration":63,"passed_time":2.986775998,"remaining_time":2.706765749},
{"learn":[0.9001430204],"iteration":64,"passed_time":3.034024761,"remaining_time":2.660606329},
{"learn":[0.8993721139],"iteration":65,"passed_time":3.084301034,"remaining_time":2.616982695},
{"learn":[0.8981379217],"iteration":66,"passed_time":3.133921077,"remaining_time":2.572621779},
{"learn":[0.89699515],"iteration":67,"passed_time":3.183532197,"remaining_time":2.528099098},
{"learn":[0.8959898765],"iteration":68,"passed_time":3.229831221,"remaining_time":2.480884851},
{"learn":[0.8947553577],"iteration":69,"passed_time":3.276269152,"remaining_time":2.433799941},
{"learn":[0.8934829497],"iteration":70,"passed_time":3.319127719,"remaining_time":2.384162164},
{"learn":[0.8923715787],"iteration":71,"passed_time":3.365176862,"remaining_time":2.336928377},
{"learn":[0.8907457965],"iteration":72,"passed_time":3.410759127,"remaining_time":2.289413661},
{"learn":[0.8894924571],"iteration":73,"passed_time":3.453733854,"remaining_time":2.240259797},
{"learn":[0.8888084255],"iteration":74,"passed_time":3.497226147,"remaining_time":2.191595052},
{"learn":[0.8881633502],"iteration":75,"passed_time":3.540288733,"remaining_time":2.142806338},
{"learn":[0.8869229994],"iteration":76,"passed_time":3.585644193,"remaining_time":2.095506347},
{"learn":[0.8858742088],"iteration":77,"passed_time":3.625826155,"remaining_time":2.045337831},
{"learn":[0.8839797842],"iteration":78,"passed_time":3.670509646,"remaining_time":1.997872339},
{"learn":[0.8833000525],"iteration":79,"passed_time":3.715864695,"remaining_time":1.950828965},
{"learn":[0.8821036909],"iteration":80,"passed_time":3.76600076,"remaining_time":1.906247298},
{"learn":[0.8814155338],"iteration":81,"passed_time":3.81812808,"remaining_time":1.862501503},
{"learn":[0.8806718188],"iteration":82,"passed_time":3.865199041,"remaining_time":1.816177863},
{"learn":[0.8797642107],"iteration":83,"passed_time":3.908949977,"remaining_time":1.768334514},
{"learn":[0.8783116661],"iteration":84,"passed_time":3.950807069,"remaining_time":1.719763077},
{"learn":[0.8776767342],"iteration":85,"passed_time":3.997339793,"remaining_time":1.67330503},
{"learn":[0.8764030586],"iteration":86,"passed_time":4.043644712,"remaining_time":1.62675362},
{"learn":[0.8750074454],"iteration":87,"passed_time":4.087571334,"remaining_time":1.579288925},
{"learn":[0.8736775406],"iteration":88,"passed_time":4.129460104,"remaining_time":1.531148129},
{"learn":[0.8718463371],"iteration":89,"passed_time":4.172000412,"remaining_time":1.483377924},
{"learn":[0.8709330149],"iteration":90,"passed_time":4.2118584,"remaining_time":1.434808906},
{"learn":[0.8699991639],"iteration":91,"passed_time":4.257750101,"remaining_time":1.388396772},
{"learn":[0.8691600304],"iteration":92,"passed_time":4.304681611,"remaining_time":1.342320072},
{"learn":[0.8678832427],"iteration":93,"passed_time":4.349215587,"remaining_time":1.295511026},
{"learn":[0.8664975597],"iteration":94,"passed_time":4.394448393,"remaining_time":1.248948491},
{"learn":[0.8658075731],"iteration":95,"passed_time":4.435015961,"remaining_time":1.201150156},
{"learn":[0.8650639011],"iteration":96,"passed_time":4.477909307,"remaining_time":1.154100337},
{"learn":[0.8645719779],"iteration":97,"passed_time":4.524136563,"remaining_time":1.107951811},
{"learn":[0.8639876984],"iteration":98,"passed_time":4.571052353,"remaining_time":1.061961658},
{"learn":[0.8631646069],"iteration":99,"passed_time":4.612717965,"remaining_time":1.014797952},
{"learn":[0.8617088409],"iteration":100,"passed_time":4.656668717,"remaining_time":0.9682182481},
{"learn":[0.8606556529],"iteration":101,"passed_time":4.70229899,"remaining_time":0.9220194098},
{"learn":[0.8587786373],"iteration":102,"passed_time":4.746649735,"remaining_time":0.8755955821},
{"learn":[0.8581848699],"iteration":103,"passed_time":4.796165018,"remaining_time":0.8301054838},
{"learn":[0.8574318952],"iteration":104,"passed_time":4.844077229,"remaining_time":0.7842791703},
{"learn":[0.8561346764],"iteration":105,"passed_time":4.890519879,"remaining_time":0.7381916798},
{"learn":[0.8551106309],"iteration":106,"passed_time":4.936870432,"remaining_time":0.6920846399},
{"learn":[0.8541515971],"iteration":107,"passed_time":4.979171185,"remaining_time":0.6454481166},
{"learn":[0.8537996746],"iteration":108,"passed_time":5.02048238,"remaining_time":0.5987731279},
{"learn":[0.8525474965],"iteration":109,"passed_time":5.062780789,"remaining_time":0.5523033588},
{"learn":[0.8513197468],"iteration":110,"passed_time":5.105607709,"remaining_time":0.5059611243},
{"learn":[0.8498407682],"iteration":111,"passed_time":5.150565982,"remaining_time":0.4598719627},
{"learn":[0.8487958228],"iteration":112,"passed_time":5.19513419,"remaining_time":0.4137717496},
{"learn":[0.8477022448],"iteration":113,"passed_time":5.243271332,"remaining_time":0.3679488654},
{"learn":[0.8470302437],"iteration":114,"passed_time":5.285492819,"remaining_time":0.3217256498},
{"learn":[0.846603734],"iteration":115,"passed_time":5.331144411,"remaining_time":0.2757488488},
{"learn":[0.8457795882],"iteration":116,"passed_time":5.376839565,"remaining_time":0.2297794686},
{"learn":[0.8447283663],"iteration":117,"passed_time":5.425245663,"remaining_time":0.1839066326},
{"learn":[0.8437061028],"iteration":118,"passed_time":5.479825134,"remaining_time":0.1381468521},
{"learn":[0.8429188642],"iteration":119,"passed_time":5.536131915,"remaining_time":0.09226886525},
{"learn":[0.842356634],"iteration":120,"passed_time":5.583908648,"remaining_time":0.04614800536},
{"learn":[0.8411461083],"iteration":121,"passed_time":5.630573612,"remaining_time":0}
]}